sekit/__init__.py
sekit/eio/__init__.py
sekit/eio/eio.py
sekit/jymatplot/__init__.py
sekit/jymatplot/__main__.py
sekit/jymatplot/simple_matplot.py
sekit/search/__init__.py
sekit/search/__main__.py
sekit/search/search.py
sekit/spartan/Cluster.py
sekit/spartan/ComputeNode.py
sekit/spartan/Spartan.py
sekit/spartan/SshComputeNode.py
sekit/spartan/__init__.py
sekit/spartan/__main__.py
sekit/spartan/gen_param.py
sekit/spartan/spartan
sekit/stats/__init__.py
sekit/stats/__main__.py
sekit/stats/stats.py
sekit/utils/ParamEncoder.py
sekit/utils/__init__.py
sekit/utils/convert_param_to_list.py
sekit/utils/load_yaml_or_json.py
sekit/utils/make_param_str.py
sekit/utils/support_numpy.py
sekit/utils/transform_param_value.py
sekit-1.0.0.dist-info/LICENSE
sekit-1.0.0.dist-info/METADATA
sekit-1.0.0.dist-info/WHEEL
sekit-1.0.0.dist-info/entry_points.txt
sekit-1.0.0.dist-info/RECORD
