Metadata-Version: 2.1
Name: sekit
Version: 1.0.0
Summary: Python tools to support scientific computing experiments.
Home-page: https://github.com/HidetoshiKawaguchi/sekit
License: MIT
Author: Hidetoshi Kawaguchi
Author-email: kawa.hide39@gmail.com
Requires-Python: >=3.11,<4.0
Classifier: License :: OSI Approved :: MIT License
Classifier: Programming Language :: Python :: 3
Classifier: Programming Language :: Python :: 3.11
Classifier: Programming Language :: Python :: 3.12
Requires-Dist: matplotlib (>=3.9.1,<4.0.0)
Requires-Dist: pandas (>=2.2.2,<3.0.0)
Requires-Dist: pyyaml (>=6.0.1,<7.0.0)
Project-URL: Documentation, https://github.com/HidetoshiKawaguchi/sekit
Project-URL: Repository, https://github.com/HidetoshiKawaguchi/sekit
